{
  "20130620": {
    "colors": {
      "background": "#87bcb4"
    },
    "images": {
      "small": "{img}/20130620/default@2x.jpg!jpg85",
      "small2x": "{img}/20130620/default@2x.jpg!jpg85",
      "small568h2x": "{img}/20130620/default-568h@2x.jpg!jpg85",
      "big": "{img}/20130620/big.jpg!jpg85",
      "big2x": "{img}/20130620/big@2x.jpg!jpg85",
      "big568h2x": "{img}/20130620/big-568h@2x.jpg!jpg85"
    },
    "text": {
      "comment1": "小事构成整个生活",
      "comment2": "Saigon,越南.希望这个夏天能持续上一百年"
    },
    "event": "",
    "music": {
      "name": "You're Beautiful",
      "artist": "邓福如",
      "url": "{music}/20130620/0620_conv.mp3",
      "nitingCode": "INVALID_1371535710162"
    },
    "modifiedAt": "2014-09-01T03:32:36.000Z"
  }
}