{
  "20130630": {
    "colors": {
      "background": "#fd7540"
    },
    "images": {
      "small": "{img}/20130630/default@2x.jpg!jpg85",
      "small2x": "{img}/20130630/default@2x.jpg!jpg85",
      "small568h2x": "{img}/20130630/default-568h@2x.jpg!jpg85",
      "big": "{img}/20130630/big.jpg!jpg85",
      "big2x": "{img}/20130630/big@2x.jpg!jpg85",
      "big568h2x": "{img}/20130630/big-568h@2x.jpg!jpg85"
    },
    "text": {
      "comment1": "在这里,星星变大变亮",
      "comment2": "Mykonos,希腊.直起腰,我望见蓝色大海和帆影"
    },
    "event": "",
    "music": {
      "name": "One Day",
      "artist": "Matisyahu",
      "url": "{music}/20130630/0630.mp3",
      "nitingCode": "INVALID_1372044357442"
    },
    "modifiedAt": "2013-06-24T03:25:57.000Z"
  }
}