{
  "20130323": {
    "colors": {
      "background": "#fe3245"
    },
    "images": {
      "small": "{img}/20130323/default@2x.jpg",
      "small2x": "{img}/20130323/default@2x.jpg",
      "small568h2x": "{img}/20130323/default-568h@2x.jpg",
      "big": "{img}/20130323/big.jpg",
      "big2x": "{img}/20130323/big@2x.jpg",
      "big568h2x": "{img}/20130323/big-568h@2x.jpg"
    },
    "text": {
      "comment1": "地球一小时",
      "comment2": "三亚,海南.心思随意飘摇,等着暴雨带来的舞蹈"
    },
    "event": "",
    "music": {
      "name": "With A Childs Heart",
      "artist": "迈克尔 杰克逊",
      "url": "{music}/20130323/M0111148005.mp3",
      "nitingCode": "1363673382077"
    },
    "modifiedAt": "2013-03-19T08:36:44.000Z"
  }
}