{
  "20140523": {
    "colors": {
      "background": "#5bd884"
    },
    "images": {
      "small": "{img}/20140523/default@2x.jpg!jpg85",
      "small2x": "{img}/20140523/default@2x.jpg!jpg85",
      "small568h2x": "{img}/20140523/default-568h@2x.jpg!jpg85",
      "big": "{img}/20140523/big.jpg!jpg85",
      "big2x": "{img}/20140523/big@2x.jpg!jpg85",
      "big568h2x": "{img}/20140523/big-568h@2x.jpg!jpg85"
    },
    "text": {
      "comment1": "上帝别拯救女王",
      "comment2": "Seoul,韩国.也别拯救伪少女萝莉们的空想 "
    },
    "event": "",
    "music": {
      "name": "Pink Shoes",
      "artist": "IU",
      "url": "{music}/20140523/0523.mp3",
      "nitingCode": "INVALID_1400581884141"
    },
    "modifiedAt": "2014-05-20T10:31:24.000Z"
  }
}