{
  "20130524": {
    "colors": {
      "background": "#4fc6cc"
    },
    "images": {
      "small": "{img}/20130524/default@2x.jpg!jpg85",
      "small2x": "{img}/20130524/default@2x.jpg!jpg85",
      "small568h2x": "{img}/20130524/default-568h@2x.jpg!jpg85",
      "big": "{img}/20130524/big.jpg!jpg85",
      "big2x": "{img}/20130524/big@2x.jpg!jpg85",
      "big568h2x": "{img}/20130524/big-568h@2x.jpg!jpg85"
    },
    "text": {
      "comment1": "这中了毒的夏日",
      "comment2": "San Francisco,美国.我与你的相会就是一首诗"
    },
    "event": "",
    "music": {
      "name": "等等",
      "artist": "Olivia Ong",
      "url": "{music}/20130524/OliviaOng.mp3",
      "nitingCode": "INVALID_1369047220500"
    },
    "modifiedAt": "2013-05-20T10:53:40.000Z"
  }
}