{
  "20140329": {
    "colors": {
      "background": "#24b55d"
    },
    "images": {
      "small": "{img}/20140329/default@2x.jpg!jpg85",
      "small2x": "{img}/20140329/default@2x.jpg!jpg85",
      "small568h2x": "{img}/20140329/default-568h@2x.jpg!jpg85",
      "big": "{img}/20140329/big.jpg!jpg85",
      "big2x": "{img}/20140329/big@2x.jpg!jpg85",
      "big568h2x": "{img}/20140329/big-568h@2x.jpg!jpg85"
    },
    "text": {
      "comment1": "开心的凝望,你给我的太阳",
      "comment2": "Seoul,韩国.靠着一点点美好,撑着长长的迷惘"
    },
    "event": "",
    "music": {
      "name": "Problems",
      "artist": "Mother Mother",
      "url": "{music}/20140329/0329.mp3",
      "nitingCode": "INVALID_1395644454535"
    },
    "modifiedAt": "2014-03-24T07:00:54.000Z"
  }
}