{
  "20130128": {
    "colors": {
      "background": "#f99d3c"
    },
    "images": {
      "small": "{img}/20130128/default@2x.jpg",
      "small2x": "{img}/20130128/default@2x.jpg",
      "small568h2x": "{img}/20130128/default-568h@2x.jpg",
      "big": "{img}/20130128/big.jpg",
      "big2x": "{img}/20130128/big@2x.jpg",
      "big568h2x": "{img}/20130128/big-568h@2x.jpg"
    },
    "text": {
      "comment1": "心花若怒放",
      "comment2": "高雄,中国.每一个花朵都是一个天堂"
    },
    "event": "",
    "music": {
      "name": "不知所以然",
      "artist": "蔡健雅",
      "url": "{music}/20130128/4523a3584030958275b9bd94d7e94864ca0da96bbce.mp3",
      "nitingCode": "1335258150619"
    },
    "modifiedAt": "2013-01-17T06:12:35.000Z"
  }
}